s3jr/__init__.py
s3jr-0.1.0.dist-info/LICENSE
s3jr-0.1.0.dist-info/METADATA
s3jr-0.1.0.dist-info/WHEEL
s3jr-0.1.0.dist-info/top_level.txt
s3jr-0.1.0.dist-info/RECORD
