Metadata-Version: 2.1
Name: s3jr
Version: 0.1.0
Summary: A simpler s3 storage api
Home-page: https://github.com/prakis/s3jr
Author: Kishore
Author-email: prakis@gmail.com
License: BSD 2-clause
Classifier: Development Status :: 1 - Planning
Classifier: Intended Audience :: Science/Research
Classifier: License :: OSI Approved :: BSD License
Classifier: Operating System :: POSIX :: Linux
Classifier: Programming Language :: Python :: 2
Classifier: Programming Language :: Python :: 2.7
Classifier: Programming Language :: Python :: 3
Classifier: Programming Language :: Python :: 3.4
Classifier: Programming Language :: Python :: 3.5
License-File: LICENSE
Requires-Dist: mpi4py>=2.0
Requires-Dist: numpy
